{
  "duration": 97.27700680272109,
  "transcript": "In a forest, a creature found a head. He tried to put the head on his head, and he thinks it's nice. So, with putting his head on his head, he walk around, and he met a bird, but she left at him. So he left his head, and but the bird actually thought that it was cool. So the bird brought the head and used it for her house for her eggs. He reappeared and saw it again, and he took it from the bird and used it as a head again. After some time, eggs turned into a baby bird, so the baby lived on his head.",
  "n_words": 109,
  "words": [
    {
      "word": "In",
      "start": 0.23,
      "end": 0.37,
      "source": "mfa"
    },
    {
      "word": "a",
      "start": 0.37,
      "end": 0.45,
      "source": "mfa"
    },
    {
      "word": "forest",
      "start": 0.45,
      "end": 1.01,
      "source": "mfa"
    },
    {
      "word": "a",
      "start": 1.6,
      "end": 1.71,
      "source": "mfa"
    },
    {
      "word": "creature",
      "start": 1.71,
      "end": 2.27,
      "source": "mfa"
    },
    {
      "word": "found",
      "start": 2.27,
      "end": 2.89,
      "source": "mfa"
    },
    {
      "word": "a",
      "start": 3.25,
      "end": 3.47,
      "source": "mfa"
    },
    {
      "word": "head",
      "start": 3.47,
      "end": 3.78,
      "source": "mfa"
    },
    {
      "word": "He",
      "start": 7.68,
      "end": 7.89,
      "source": "mfa"
    },
    {
      "word": "tried",
      "start": 8.22,
      "end": 8.56,
      "source": "mfa"
    },
    {
      "word": "to",
      "start": 8.56,
      "end": 9.11,
      "source": "mfa"
    },
    {
      "word": "put",
      "start": 9.59,
      "end": 9.81,
      "source": "mfa"
    },
    {
      "word": "the",
      "start": 11.08,
      "end": 11.27,
      "source": "mfa"
    },
    {
      "word": "head",
      "start": 11.27,
      "end": 11.71,
      "source": "mfa"
    },
    {
      "word": "on",
      "start": 11.75,
      "end": 11.9,
      "source": "mfa"
    },
    {
      "word": "his",
      "start": 11.9,
      "end": 12.11,
      "source": "mfa"
    },
    {
      "word": "head",
      "start": 12.11,
      "end": 12.55,
      "source": "mfa"
    },
    {
      "word": "and",
      "start": 14.05,
      "end": 14.55,
      "source": "mfa"
    },
    {
      "word": "he",
      "start": 14.66,
      "end": 14.81,
      "source": "mfa"
    },
    {
      "word": "thinks",
      "start": 14.81,
      "end": 15.43,
      "source": "mfa"
    },
    {
      "word": "it's",
      "start": 16.75,
      "end": 17.01,
      "source": "mfa"
    },
    {
      "word": "nice",
      "start": 17.01,
      "end": 17.53,
      "source": "mfa"
    },
    {
      "word": "So",
      "start": 18.68,
      "end": 19.46,
      "source": "mfa"
    },
    {
      "word": "with",
      "start": 20.42,
      "end": 20.66,
      "source": "mfa"
    },
    {
      "word": "putting",
      "start": 20.66,
      "end": 21.02,
      "source": "mfa"
    },
    {
      "word": "his",
      "start": 21.02,
      "end": 21.5,
      "source": "mfa"
    },
    {
      "word": "head",
      "start": 21.5,
      "end": 21.89,
      "source": "mfa"
    },
    {
      "word": "on",
      "start": 21.89,
      "end": 22.03,
      "source": "mfa"
    },
    {
      "word": "his",
      "start": 22.03,
      "end": 22.24,
      "source": "mfa"
    },
    {
      "word": "head",
      "start": 22.24,
      "end": 22.64,
      "source": "mfa"
    },
    {
      "word": "he",
      "start": 24.05,
      "end": 24.46,
      "source": "mfa"
    },
    {
      "word": "walk",
      "start": 25.2,
      "end": 25.46,
      "source": "mfa"
    },
    {
      "word": "around",
      "start": 25.46,
      "end": 25.87,
      "source": "mfa"
    },
    {
      "word": "and",
      "start": 27.06,
      "end": 27.36,
      "source": "mfa"
    },
    {
      "word": "he",
      "start": 27.36,
      "end": 27.59,
      "source": "mfa"
    },
    {
      "word": "met",
      "start": 27.59,
      "end": 27.99,
      "source": "mfa"
    },
    {
      "word": "a",
      "start": 28.19,
      "end": 28.27,
      "source": "mfa"
    },
    {
      "word": "bird",
      "start": 28.27,
      "end": 28.78,
      "source": "mfa"
    },
    {
      "word": "but",
      "start": 29.58,
      "end": 29.68,
      "source": "mfa"
    },
    {
      "word": "she",
      "start": 32.05,
      "end": 32.75,
      "source": "mfa"
    },
    {
      "word": "left",
      "start": 32.82,
      "end": 33.09,
      "source": "mfa"
    },
    {
      "word": "at",
      "start": 33.09,
      "end": 33.23,
      "source": "mfa"
    },
    {
      "word": "him",
      "start": 33.23,
      "end": 33.66,
      "source": "mfa"
    },
    {
      "word": "So",
      "start": 35.54,
      "end": 36.09,
      "source": "mfa"
    },
    {
      "word": "he",
      "start": 36.09,
      "end": 36.33,
      "source": "mfa"
    },
    {
      "word": "left",
      "start": 36.33,
      "end": 36.69,
      "source": "mfa"
    },
    {
      "word": "his",
      "start": 36.69,
      "end": 37.03,
      "source": "mfa"
    },
    {
      "word": "head",
      "start": 37.03,
      "end": 37.43,
      "source": "mfa"
    },
    {
      "word": "and",
      "start": 38.84,
      "end": 39.5,
      "source": "mfa"
    },
    {
      "word": "but",
      "start": 39.62,
      "end": 39.69,
      "source": "mfa"
    },
    {
      "word": "the",
      "start": 40.99,
      "end": 41.14,
      "source": "mfa"
    },
    {
      "word": "bird",
      "start": 41.14,
      "end": 41.65,
      "source": "mfa"
    },
    {
      "word": "actually",
      "start": 42.92,
      "end": 43.3,
      "source": "mfa"
    },
    {
      "word": "thought",
      "start": 43.54,
      "end": 43.81,
      "source": "mfa"
    },
    {
      "word": "that",
      "start": 43.81,
      "end": 44.07,
      "source": "mfa"
    },
    {
      "word": "it",
      "start": 44.51,
      "end": 44.59,
      "source": "mfa"
    },
    {
      "word": "was",
      "start": 44.59,
      "end": 44.74,
      "source": "mfa"
    },
    {
      "word": "cool",
      "start": 44.74,
      "end": 45.14,
      "source": "mfa"
    },
    {
      "word": "So",
      "start": 47.04,
      "end": 47.62,
      "source": "mfa"
    },
    {
      "word": "the",
      "start": 49.78,
      "end": 49.94,
      "source": "mfa"
    },
    {
      "word": "bird",
      "start": 49.94,
      "end": 50.36,
      "source": "mfa"
    },
    {
      "word": "brought",
      "start": 50.98,
      "end": 51.3,
      "source": "mfa"
    },
    {
      "word": "the",
      "start": 51.3,
      "end": 51.42,
      "source": "mfa"
    },
    {
      "word": "head",
      "start": 51.42,
      "end": 51.93,
      "source": "mfa"
    },
    {
      "word": "and",
      "start": 52.14,
      "end": 52.63,
      "source": "mfa"
    },
    {
      "word": "used",
      "start": 52.63,
      "end": 53.0,
      "source": "mfa"
    },
    {
      "word": "it",
      "start": 53.0,
      "end": 53.22,
      "source": "mfa"
    },
    {
      "word": "for",
      "start": 53.22,
      "end": 53.96,
      "source": "mfa"
    },
    {
      "word": "her",
      "start": 56.27,
      "end": 56.8,
      "source": "mfa"
    },
    {
      "word": "house",
      "start": 57.2,
      "end": 57.59,
      "source": "mfa"
    },
    {
      "word": "for",
      "start": 57.59,
      "end": 58.04,
      "source": "mfa"
    },
    {
      "word": "her",
      "start": 59.91,
      "end": 60.31,
      "source": "mfa"
    },
    {
      "word": "eggs",
      "start": 60.45,
      "end": 61.08,
      "source": "mfa"
    },
    {
      "word": "He",
      "start": 64.43,
      "end": 64.74,
      "source": "mfa"
    },
    {
      "word": "reappeared",
      "start": 64.74,
      "end": 65.55,
      "source": "mfa"
    },
    {
      "word": "and",
      "start": 65.55,
      "end": 66.04,
      "source": "mfa"
    },
    {
      "word": "saw",
      "start": 66.36,
      "end": 66.68,
      "source": "mfa"
    },
    {
      "word": "it",
      "start": 66.68,
      "end": 66.89,
      "source": "mfa"
    },
    {
      "word": "again",
      "start": 67.02,
      "end": 67.56,
      "source": "mfa"
    },
    {
      "word": "and",
      "start": 68.13,
      "end": 68.75,
      "source": "mfa"
    },
    {
      "word": "he",
      "start": 68.94,
      "end": 69.08,
      "source": "mfa"
    },
    {
      "word": "took",
      "start": 69.08,
      "end": 69.4,
      "source": "mfa"
    },
    {
      "word": "it",
      "start": 69.4,
      "end": 69.53,
      "source": "mfa"
    },
    {
      "word": "from",
      "start": 70.18,
      "end": 70.48,
      "source": "mfa"
    },
    {
      "word": "the",
      "start": 70.48,
      "end": 70.6,
      "source": "mfa"
    },
    {
      "word": "bird",
      "start": 70.6,
      "end": 71.0,
      "source": "mfa"
    },
    {
      "word": "and",
      "start": 71.58,
      "end": 72.06,
      "source": "mfa"
    },
    {
      "word": "used",
      "start": 72.09,
      "end": 72.45,
      "source": "mfa"
    },
    {
      "word": "it",
      "start": 72.45,
      "end": 72.76,
      "source": "mfa"
    },
    {
      "word": "as",
      "start": 72.9,
      "end": 73.2,
      "source": "mfa"
    },
    {
      "word": "a",
      "start": 73.2,
      "end": 73.29,
      "source": "mfa"
    },
    {
      "word": "head",
      "start": 73.29,
      "end": 73.64,
      "source": "mfa"
    },
    {
      "word": "again",
      "start": 73.69,
      "end": 74.28,
      "source": "mfa"
    },
    {
      "word": "After",
      "start": 77.47,
      "end": 77.75,
      "source": "mfa"
    },
    {
      "word": "some",
      "start": 78.86,
      "end": 79.09,
      "source": "mfa"
    },
    {
      "word": "time",
      "start": 79.09,
      "end": 79.64,
      "source": "mfa"
    },
    {
      "word": "eggs",
      "start": 86.25,
      "end": 86.32,
      "source": "mfa"
    },
    {
      "word": "turned",
      "start": 86.32,
      "end": 86.56,
      "source": "mfa"
    },
    {
      "word": "into",
      "start": 86.56,
      "end": 87.18,
      "source": "mfa"
    },
    {
      "word": "a",
      "start": 87.45,
      "end": 88.23,
      "source": "mfa"
    },
    {
      "word": "baby",
      "start": 88.9,
      "end": 89.51,
      "source": "mfa"
    },
    {
      "word": "bird",
      "start": 89.86,
      "end": 90.28,
      "source": "mfa"
    },
    {
      "word": "so",
      "start": 91.14,
      "end": 91.53,
      "source": "mfa"
    },
    {
      "word": "the",
      "start": 91.53,
      "end": 91.72,
      "source": "mfa"
    },
    {
      "word": "baby",
      "start": 91.72,
      "end": 92.36,
      "source": "mfa"
    },
    {
      "word": "lived",
      "start": 94.32,
      "end": 94.79,
      "source": "mfa"
    },
    {
      "word": "on",
      "start": 94.79,
      "end": 95.22,
      "source": "mfa"
    },
    {
      "word": "his",
      "start": 95.9,
      "end": 96.21,
      "source": "mfa"
    },
    {
      "word": "head",
      "start": 96.21,
      "end": 96.51,
      "source": "mfa"
    }
  ],
  "filler_augmentation": {
    "mfa_word_count": 173,
    "filler_injected": 64,
    "filler_consumed": 64,
    "fallback_count": 0,
    "skipped_mfa_tokens": 0
  }
}