{
  "duration": 46.684988662131516,
  "transcript": "While looking for food, Fat Bird found a nice little top hat. He went to try it on and thought he looked pretty good. As he was walking along, he came up to Tall Bird. Tall Bird observed his hat and immediately began to laugh as it looked absolutely ridiculous on Fat Bird. Fat Bird then dropped it and Skinny Bird, being the capable bird that he was, took the hat with him and proceeded to plant an egg within the hat. Fat Bird came back looking for his hat and stole it away from Skinny Bird or from Tall Bird. While while Tall Bird angrily glared at Fat Bird, suddenly the hat popped off, and so was born Tiny Bird on Fat Bird's head.",
  "n_words": 125,
  "words": [
    {
      "word": "While",
      "start": 0.19,
      "end": 0.39,
      "source": "mfa"
    },
    {
      "word": "looking",
      "start": 0.39,
      "end": 0.71,
      "source": "mfa"
    },
    {
      "word": "for",
      "start": 0.71,
      "end": 0.89,
      "source": "mfa"
    },
    {
      "word": "food",
      "start": 0.89,
      "end": 1.28,
      "source": "mfa"
    },
    {
      "word": "Fat",
      "start": 1.86,
      "end": 2.23,
      "source": "mfa"
    },
    {
      "word": "Bird",
      "start": 2.23,
      "end": 2.6,
      "source": "mfa"
    },
    {
      "word": "found",
      "start": 2.85,
      "end": 3.17,
      "source": "mfa"
    },
    {
      "word": "a",
      "start": 3.17,
      "end": 3.2,
      "source": "mfa"
    },
    {
      "word": "nice",
      "start": 3.2,
      "end": 3.54,
      "source": "mfa"
    },
    {
      "word": "little",
      "start": 3.54,
      "end": 3.7,
      "source": "mfa"
    },
    {
      "word": "top",
      "start": 3.7,
      "end": 4.01,
      "source": "mfa"
    },
    {
      "word": "hat",
      "start": 4.01,
      "end": 4.24,
      "source": "mfa"
    },
    {
      "word": "He",
      "start": 4.82,
      "end": 4.94,
      "source": "mfa"
    },
    {
      "word": "went",
      "start": 4.94,
      "end": 5.14,
      "source": "mfa"
    },
    {
      "word": "to",
      "start": 5.14,
      "end": 5.21,
      "source": "mfa"
    },
    {
      "word": "try",
      "start": 5.21,
      "end": 5.5,
      "source": "mfa"
    },
    {
      "word": "it",
      "start": 5.5,
      "end": 5.56,
      "source": "mfa"
    },
    {
      "word": "on",
      "start": 5.56,
      "end": 5.83,
      "source": "mfa"
    },
    {
      "word": "and",
      "start": 5.83,
      "end": 5.96,
      "source": "mfa"
    },
    {
      "word": "thought",
      "start": 5.96,
      "end": 6.11,
      "source": "mfa"
    },
    {
      "word": "he",
      "start": 6.11,
      "end": 6.21,
      "source": "mfa"
    },
    {
      "word": "looked",
      "start": 6.21,
      "end": 6.46,
      "source": "mfa"
    },
    {
      "word": "pretty",
      "start": 6.46,
      "end": 6.66,
      "source": "mfa"
    },
    {
      "word": "good",
      "start": 6.66,
      "end": 6.99,
      "source": "mfa"
    },
    {
      "word": "As",
      "start": 7.78,
      "end": 7.89,
      "source": "mfa"
    },
    {
      "word": "he",
      "start": 7.89,
      "end": 7.95,
      "source": "mfa"
    },
    {
      "word": "was",
      "start": 7.95,
      "end": 8.05,
      "source": "mfa"
    },
    {
      "word": "walking",
      "start": 8.05,
      "end": 8.46,
      "source": "mfa"
    },
    {
      "word": "along",
      "start": 8.46,
      "end": 8.81,
      "source": "mfa"
    },
    {
      "word": "he",
      "start": 8.81,
      "end": 8.9,
      "source": "mfa"
    },
    {
      "word": "came",
      "start": 8.9,
      "end": 9.2,
      "source": "mfa"
    },
    {
      "word": "up",
      "start": 9.2,
      "end": 9.35,
      "source": "mfa"
    },
    {
      "word": "to",
      "start": 9.35,
      "end": 9.45,
      "source": "mfa"
    },
    {
      "word": "Tall",
      "start": 9.45,
      "end": 9.71,
      "source": "mfa"
    },
    {
      "word": "Bird",
      "start": 9.71,
      "end": 10.02,
      "source": "mfa"
    },
    {
      "word": "Tall",
      "start": 10.98,
      "end": 11.17,
      "source": "mfa"
    },
    {
      "word": "Bird",
      "start": 11.17,
      "end": 11.48,
      "source": "mfa"
    },
    {
      "word": "observed",
      "start": 11.99,
      "end": 12.49,
      "source": "mfa"
    },
    {
      "word": "his",
      "start": 12.49,
      "end": 12.62,
      "source": "mfa"
    },
    {
      "word": "hat",
      "start": 12.62,
      "end": 13.05,
      "source": "mfa"
    },
    {
      "word": "and",
      "start": 13.4,
      "end": 13.96,
      "source": "mfa"
    },
    {
      "word": "immediately",
      "start": 14.15,
      "end": 14.63,
      "source": "mfa"
    },
    {
      "word": "began",
      "start": 14.63,
      "end": 15.01,
      "source": "mfa"
    },
    {
      "word": "to",
      "start": 15.01,
      "end": 15.13,
      "source": "mfa"
    },
    {
      "word": "laugh",
      "start": 15.13,
      "end": 15.64,
      "source": "mfa"
    },
    {
      "word": "as",
      "start": 15.7,
      "end": 15.88,
      "source": "mfa"
    },
    {
      "word": "it",
      "start": 15.88,
      "end": 16.03,
      "source": "mfa"
    },
    {
      "word": "looked",
      "start": 16.03,
      "end": 16.27,
      "source": "mfa"
    },
    {
      "word": "absolutely",
      "start": 16.35,
      "end": 16.85,
      "source": "mfa"
    },
    {
      "word": "ridiculous",
      "start": 16.85,
      "end": 17.49,
      "source": "mfa"
    },
    {
      "word": "on",
      "start": 17.55,
      "end": 17.7,
      "source": "mfa"
    },
    {
      "word": "Fat",
      "start": 17.7,
      "end": 18.0,
      "source": "mfa"
    },
    {
      "word": "Bird",
      "start": 18.0,
      "end": 18.24,
      "source": "mfa"
    },
    {
      "word": "Fat",
      "start": 19.19,
      "end": 19.41,
      "source": "mfa"
    },
    {
      "word": "Bird",
      "start": 19.41,
      "end": 19.62,
      "source": "mfa"
    },
    {
      "word": "then",
      "start": 19.62,
      "end": 19.8,
      "source": "mfa"
    },
    {
      "word": "dropped",
      "start": 19.8,
      "end": 20.19,
      "source": "mfa"
    },
    {
      "word": "it",
      "start": 20.19,
      "end": 20.4,
      "source": "mfa"
    },
    {
      "word": "and",
      "start": 20.74,
      "end": 20.83,
      "source": "mfa"
    },
    {
      "word": "Skinny",
      "start": 20.83,
      "end": 21.1,
      "source": "mfa"
    },
    {
      "word": "Bird",
      "start": 21.1,
      "end": 21.48,
      "source": "mfa"
    },
    {
      "word": "being",
      "start": 21.63,
      "end": 22.06,
      "source": "mfa"
    },
    {
      "word": "the",
      "start": 22.06,
      "end": 22.45,
      "source": "mfa"
    },
    {
      "word": "capable",
      "start": 23.03,
      "end": 23.48,
      "source": "mfa"
    },
    {
      "word": "bird",
      "start": 23.48,
      "end": 23.76,
      "source": "mfa"
    },
    {
      "word": "that",
      "start": 23.76,
      "end": 23.87,
      "source": "mfa"
    },
    {
      "word": "he",
      "start": 23.87,
      "end": 23.96,
      "source": "mfa"
    },
    {
      "word": "was",
      "start": 23.96,
      "end": 24.52,
      "source": "mfa"
    },
    {
      "word": "took",
      "start": 24.68,
      "end": 24.85,
      "source": "mfa"
    },
    {
      "word": "the",
      "start": 24.85,
      "end": 24.94,
      "source": "mfa"
    },
    {
      "word": "hat",
      "start": 24.94,
      "end": 25.15,
      "source": "mfa"
    },
    {
      "word": "with",
      "start": 25.15,
      "end": 25.35,
      "source": "mfa"
    },
    {
      "word": "him",
      "start": 25.35,
      "end": 25.7,
      "source": "mfa"
    },
    {
      "word": "and",
      "start": 25.96,
      "end": 26.08,
      "source": "mfa"
    },
    {
      "word": "proceeded",
      "start": 26.08,
      "end": 26.5,
      "source": "mfa"
    },
    {
      "word": "to",
      "start": 26.5,
      "end": 26.57,
      "source": "mfa"
    },
    {
      "word": "plant",
      "start": 26.57,
      "end": 27.03,
      "source": "mfa"
    },
    {
      "word": "an",
      "start": 27.16,
      "end": 27.29,
      "source": "mfa"
    },
    {
      "word": "egg",
      "start": 27.29,
      "end": 27.55,
      "source": "mfa"
    },
    {
      "word": "within",
      "start": 27.85,
      "end": 28.16,
      "source": "mfa"
    },
    {
      "word": "the",
      "start": 28.16,
      "end": 28.22,
      "source": "mfa"
    },
    {
      "word": "hat",
      "start": 28.22,
      "end": 28.59,
      "source": "mfa"
    },
    {
      "word": "Fat",
      "start": 29.41,
      "end": 29.68,
      "source": "mfa"
    },
    {
      "word": "Bird",
      "start": 29.68,
      "end": 29.91,
      "source": "mfa"
    },
    {
      "word": "came",
      "start": 29.91,
      "end": 30.17,
      "source": "mfa"
    },
    {
      "word": "back",
      "start": 30.17,
      "end": 30.55,
      "source": "mfa"
    },
    {
      "word": "looking",
      "start": 30.55,
      "end": 30.84,
      "source": "mfa"
    },
    {
      "word": "for",
      "start": 30.84,
      "end": 31.0,
      "source": "mfa"
    },
    {
      "word": "his",
      "start": 31.0,
      "end": 31.15,
      "source": "mfa"
    },
    {
      "word": "hat",
      "start": 31.15,
      "end": 31.37,
      "source": "mfa"
    },
    {
      "word": "and",
      "start": 31.41,
      "end": 31.56,
      "source": "mfa"
    },
    {
      "word": "stole",
      "start": 31.69,
      "end": 32.16,
      "source": "mfa"
    },
    {
      "word": "it",
      "start": 32.16,
      "end": 32.23,
      "source": "mfa"
    },
    {
      "word": "away",
      "start": 32.23,
      "end": 32.65,
      "source": "mfa"
    },
    {
      "word": "from",
      "start": 32.65,
      "end": 32.88,
      "source": "mfa"
    },
    {
      "word": "Skinny",
      "start": 32.88,
      "end": 33.21,
      "source": "mfa"
    },
    {
      "word": "Bird",
      "start": 33.21,
      "end": 33.63,
      "source": "mfa"
    },
    {
      "word": "or",
      "start": 33.66,
      "end": 33.76,
      "source": "mfa"
    },
    {
      "word": "from",
      "start": 33.76,
      "end": 33.91,
      "source": "mfa"
    },
    {
      "word": "Tall",
      "start": 33.91,
      "end": 34.13,
      "source": "mfa"
    },
    {
      "word": "Bird",
      "start": 34.13,
      "end": 34.43,
      "source": "mfa"
    },
    {
      "word": "While",
      "start": 35.68,
      "end": 36.09,
      "source": "mfa"
    },
    {
      "word": "while",
      "start": 36.44,
      "end": 36.65,
      "source": "mfa"
    },
    {
      "word": "Tall",
      "start": 37.13,
      "end": 37.4,
      "source": "mfa"
    },
    {
      "word": "Bird",
      "start": 37.4,
      "end": 37.69,
      "source": "mfa"
    },
    {
      "word": "angrily",
      "start": 37.72,
      "end": 38.14,
      "source": "mfa"
    },
    {
      "word": "glared",
      "start": 38.14,
      "end": 38.63,
      "source": "mfa"
    },
    {
      "word": "at",
      "start": 38.63,
      "end": 38.76,
      "source": "mfa"
    },
    {
      "word": "Fat",
      "start": 38.76,
      "end": 39.1,
      "source": "mfa"
    },
    {
      "word": "Bird",
      "start": 39.1,
      "end": 39.44,
      "source": "mfa"
    },
    {
      "word": "suddenly",
      "start": 39.7,
      "end": 40.31,
      "source": "mfa"
    },
    {
      "word": "the",
      "start": 40.48,
      "end": 40.56,
      "source": "mfa"
    },
    {
      "word": "hat",
      "start": 40.56,
      "end": 40.85,
      "source": "mfa"
    },
    {
      "word": "popped",
      "start": 40.9,
      "end": 41.21,
      "source": "mfa"
    },
    {
      "word": "off",
      "start": 41.21,
      "end": 41.55,
      "source": "mfa"
    },
    {
      "word": "and",
      "start": 42.05,
      "end": 42.34,
      "source": "mfa"
    },
    {
      "word": "so",
      "start": 42.34,
      "end": 42.86,
      "source": "mfa"
    },
    {
      "word": "was",
      "start": 43.08,
      "end": 43.29,
      "source": "mfa"
    },
    {
      "word": "born",
      "start": 43.29,
      "end": 43.75,
      "source": "mfa"
    },
    {
      "word": "Tiny",
      "start": 43.85,
      "end": 44.11,
      "source": "mfa"
    },
    {
      "word": "Bird",
      "start": 44.11,
      "end": 44.5,
      "source": "mfa"
    },
    {
      "word": "on",
      "start": 44.8,
      "end": 45.05,
      "source": "mfa"
    },
    {
      "word": "Fat",
      "start": 45.05,
      "end": 45.34,
      "source": "mfa"
    },
    {
      "word": "Bird's",
      "start": 45.4,
      "end": 45.64,
      "source": "mfa"
    },
    {
      "word": "head",
      "start": 45.64,
      "end": 46.02,
      "source": "mfa"
    }
  ],
  "filler_augmentation": {
    "mfa_word_count": 142,
    "filler_injected": 17,
    "filler_consumed": 17,
    "fallback_count": 0,
    "skipped_mfa_tokens": 0
  }
}